jupyter_xprahtml5_proxy/__init__.py
jupyter_xprahtml5_proxy/bin/xpra.in
jupyter_xprahtml5_proxy/icons/xpra-logo.svg
jupyter_xprahtml5_proxy-0.3.5.dist-info/LICENSE
jupyter_xprahtml5_proxy-0.3.5.dist-info/METADATA
jupyter_xprahtml5_proxy-0.3.5.dist-info/WHEEL
jupyter_xprahtml5_proxy-0.3.5.dist-info/entry_points.txt
jupyter_xprahtml5_proxy-0.3.5.dist-info/top_level.txt
jupyter_xprahtml5_proxy-0.3.5.dist-info/RECORD
