Metadata-Version: 2.1
Name: jupyter-xprahtml5-proxy
Version: 0.3.5
Summary: Xpra for JupyterLab
Home-page: https://github.com/FZJ-JSC/jupyter-xprahtml5-proxy
Author: Jens Henrik Goebbert
Author-email: j.goebbert@fz-juelich.de
License: UNKNOWN
Download-URL: https://github.com/FZJ-JSC/jupyter-xprahtml5-proxy/archive/v0.3.5.tar.gz
Keywords: jupyter,xpra,jupyterhub,jupyter-server-proxy
Platform: UNKNOWN
Classifier: Programming Language :: Python :: 3
Classifier: License :: OSI Approved :: BSD License
Classifier: Operating System :: OS Independent
Classifier: Framework :: Jupyter
Requires-Python: >=3.6
Requires-Dist: jupyter-server-proxy (>=3.1.0)
